{"distrito":12,"resumenVotacion":{"acumulados":{"total":36122,"porcentaje":96.3485},"nulos":{"total":1359,"porcentaje":3.6249},"noRegistradas":{"total":10,"porcentaje":0.0267},"totalVotos":{"total":37491}},"votosCandidatura":[{"candidato":"Leroy Cavadilla Rubina","votos":5359,"porcentaje":14.2941,"partidosDetalle":[],"ganador":false,"candidatura":"pri-verde-nueva alianza-ps","imagen":"leroy.jpg","idDistrito":12},{"candidato":"Edwin Vidaurre Zulueta","votos":4115,"porcentaje":10.9760,"partidosDetalle":[],"ganador":false,"candidatura":"movimiento ciudadano","imagen":"edwin.jpg","idDistrito":12},{"candidato":"Araceli Aramberri Malvido","votos":5340,"porcentaje":14.2434,"partidosDetalle":[{"partido":"PAN-PRD-PAC","votos":65,"porcentaje":0.1734},{"partido":"PAN","votos":2178,"porcentaje":5.8094},{"partido":"PRD","votos":2391,"porcentaje":6.3775},{"partido":"PAC","votos":624,"porcentaje":1.6644},{"partido":"PAN-PRD","votos":65,"porcentaje":0.1734},{"partido":"PAN-PAC","votos":7,"porcentaje":0.0187},{"partido":"PRD-PAC","votos":10,"porcentaje":0.0267}],"ganador":false,"candidatura":"PAN-PRD-PAC","imagen":"araceli.jpg","idDistrito":12},{"candidato":"Arnau Rodrigo Cue","votos":21308,"porcentaje":56.8350,"partidosDetalle":[{"partido":"PT-morena-encuentro social","votos":540,"porcentaje":1.4403},{"partido":"PT","votos":1340,"porcentaje":3.5742},{"partido":"morena","votos":18406,"porcentaje":49.0944},{"partido":"encuentro social","votos":653,"porcentaje":1.7418},{"partido":"PT-morena","votos":160,"porcentaje":0.4268},{"partido":"PT-encuentro social","votos":18,"porcentaje":0.0480},{"partido":"morena-encuentro social","votos":191,"porcentaje":0.5095}],"ganador":false,"candidatura":"PT-morena-encuentro social","imagen":"arnua.jpg","idDistrito":12},{"candidato":null,"votos":10,"porcentaje":0.0267,"partidosDetalle":[],"ganador":false,"candidatura":"candidatos no registrados","imagen":null,"idDistrito":12},{"candidato":null,"votos":1359,"porcentaje":3.6249,"partidosDetalle":[],"ganador":false,"candidatura":"votos nulos","imagen":null,"idDistrito":12}],"estadisticas":{"actas":{"capturadas":{"total":87,"porcentaje":81.3084},"contabilizadas":{"total":87,"porcentaje":81.3084},"esperadas":{"total":107,"porcentaje":100.0}},"listaNominal":55167,"participacionCiudadana":67.9591}}