[{"SeccionID":538,"Seccion":"Sección 538","actasContabilizadas":[{"NombreCandidatura":"PAN","Votos":177,"Porcentaje":15.0895,"orden":0},{"NombreCandidatura":"PRI","Votos":69,"Porcentaje":5.8824,"orden":0},{"NombreCandidatura":"PRD","Votos":47,"Porcentaje":4.0068,"orden":0},{"NombreCandidatura":"PT","Votos":204,"Porcentaje":17.3913,"orden":0},{"NombreCandidatura":"VERDE","Votos":154,"Porcentaje":13.1287,"orden":0},{"NombreCandidatura":"MOVIMIENTO CIUDADANO","Votos":148,"Porcentaje":12.6172,"orden":0},{"NombreCandidatura":"PES TLAX","Votos":33,"Porcentaje":2.8133,"orden":0},{"NombreCandidatura":"RSP","Votos":25,"Porcentaje":2.1313,"orden":0},{"NombreCandidatura":"FUERZA SOCIAL POR MÉXICO","Votos":4,"Porcentaje":0.3410,"orden":0},{"NombreCandidatura":"CANDIDATO INDEPENDIENTE","Votos":98,"Porcentaje":8.3546,"orden":0},{"NombreCandidatura":"PAC","Votos":41,"Porcentaje":3.4953,"orden":0},{"NombreCandidatura":"PS","Votos":27,"Porcentaje":2.3018,"orden":0},{"NombreCandidatura":"MORENA","Votos":65,"Porcentaje":5.5413,"orden":0},{"NombreCandidatura":"NUEVA ALIANZA TLAX","Votos":20,"Porcentaje":1.7050,"orden":0},{"NombreCandidatura":"ENCUENTRO SOCIAL","Votos":4,"Porcentaje":0.3410,"orden":0},{"NombreCandidatura":"IMPACTO SOCIAL SÍ","Votos":15,"Porcentaje":1.2788,"orden":0}],"resumenVotacion":{"acumulados":{"total":1131,"porcentaje":96.4194},"nulos":{"total":42,"porcentaje":3.5806},"noRegistradas":{"total":0,"porcentaje":0.0},"totalVotos":{"total":1173}},"detalleVotosCasillas":[{"detalleCasilla":{"Id":"00654C9451935F679F9BDAFD93BB82DD8B6F07F69CC6D2D97422E4B42C9DA724","Casilla":"CONTIGUA 03","ClaveURL":"contigua3","ViaDigitalizacion":1},"candVotTabla":[{"Partido":"PAN","Votos":54,"Porcentaje":14.6739,"orden":0},{"Partido":"PRI","Votos":31,"Porcentaje":8.4239,"orden":0},{"Partido":"PRD","Votos":10,"Porcentaje":2.7174,"orden":0},{"Partido":"PT","Votos":50,"Porcentaje":13.5870,"orden":0},{"Partido":"VERDE","Votos":54,"Porcentaje":14.6739,"orden":0},{"Partido":"MOVIMIENTO CIUDADANO","Votos":42,"Porcentaje":11.4130,"orden":0},{"Partido":"PES TLAX","Votos":12,"Porcentaje":3.2609,"orden":0},{"Partido":"RSP","Votos":11,"Porcentaje":2.9891,"orden":0},{"Partido":"FUERZA SOCIAL POR MÉXICO","Votos":0,"Porcentaje":0.0,"orden":0},{"Partido":"CANDIDATO INDEPENDIENTE","Votos":30,"Porcentaje":8.1522,"orden":0},{"Partido":"PAC","Votos":18,"Porcentaje":4.8913,"orden":0},{"Partido":"PS","Votos":7,"Porcentaje":1.9022,"orden":0},{"Partido":"MORENA","Votos":19,"Porcentaje":5.1630,"orden":0},{"Partido":"NUEVA ALIANZA TLAX","Votos":4,"Porcentaje":1.0870,"orden":0},{"Partido":"ENCUENTRO SOCIAL","Votos":1,"Porcentaje":0.2717,"orden":0},{"Partido":"IMPACTO SOCIAL SÍ","Votos":8,"Porcentaje":2.1739,"orden":0}],"resumenVotacion":{"Acumulados":{"total":351,"porcentaje":95.3804},"NoRegistradas":{"total":0,"porcentaje":0.0},"VotosNulos":{"total":17,"porcentaje":4.6196},"Total":368,"Observaciones":null},"estadistica":{"Casilla":"CONTIGUA 03","ParticipacionCiudadana":62.6917,"ListaNominal":587}},{"detalleCasilla":{"Id":"28EB6CFAADBB8D4F7560619F71341523AC039C73EEAE3037109E73D2678FB018","Casilla":"BÁSICA 01","ClaveURL":"basica1","ViaDigitalizacion":1},"candVotTabla":[{"Partido":"PAN","Votos":74,"Porcentaje":17.9612,"orden":0},{"Partido":"PRI","Votos":17,"Porcentaje":4.1262,"orden":0},{"Partido":"PRD","Votos":11,"Porcentaje":2.6699,"orden":0},{"Partido":"PT","Votos":77,"Porcentaje":18.6893,"orden":0},{"Partido":"VERDE","Votos":43,"Porcentaje":10.4369,"orden":0},{"Partido":"MOVIMIENTO CIUDADANO","Votos":73,"Porcentaje":17.7184,"orden":0},{"Partido":"PES TLAX","Votos":11,"Porcentaje":2.6699,"orden":0},{"Partido":"RSP","Votos":6,"Porcentaje":1.4563,"orden":0},{"Partido":"FUERZA SOCIAL POR MÉXICO","Votos":1,"Porcentaje":0.2427,"orden":0},{"Partido":"CANDIDATO INDEPENDIENTE","Votos":40,"Porcentaje":9.7087,"orden":0},{"Partido":"PAC","Votos":12,"Porcentaje":2.9126,"orden":0},{"Partido":"PS","Votos":12,"Porcentaje":2.9126,"orden":0},{"Partido":"MORENA","Votos":13,"Porcentaje":3.1553,"orden":0},{"Partido":"NUEVA ALIANZA TLAX","Votos":5,"Porcentaje":1.2136,"orden":0},{"Partido":"ENCUENTRO SOCIAL","Votos":3,"Porcentaje":0.7282,"orden":0},{"Partido":"IMPACTO SOCIAL SÍ","Votos":1,"Porcentaje":0.2427,"orden":0}],"resumenVotacion":{"Acumulados":{"total":399,"porcentaje":96.8447},"NoRegistradas":{"total":0,"porcentaje":0.0},"VotosNulos":{"total":13,"porcentaje":3.1553},"Total":412,"Observaciones":null},"estadistica":{"Casilla":"BÁSICA 01","ParticipacionCiudadana":70.0680,"ListaNominal":588}},{"detalleCasilla":{"Id":"C6AA69DD65DE08AB691444F4A055F5509C8F36B664F2871AEC8A854D65B8C0CB","Casilla":"CONTIGUA 01","ClaveURL":"contigua1","ViaDigitalizacion":1},"candVotTabla":[{"Partido":"PAN","Votos":49,"Porcentaje":12.4682,"orden":0},{"Partido":"PRI","Votos":21,"Porcentaje":5.3435,"orden":0},{"Partido":"PRD","Votos":26,"Porcentaje":6.6158,"orden":0},{"Partido":"PT","Votos":77,"Porcentaje":19.5929,"orden":0},{"Partido":"VERDE","Votos":57,"Porcentaje":14.5038,"orden":0},{"Partido":"MOVIMIENTO CIUDADANO","Votos":33,"Porcentaje":8.3969,"orden":0},{"Partido":"PES TLAX","Votos":10,"Porcentaje":2.5445,"orden":0},{"Partido":"RSP","Votos":8,"Porcentaje":2.0356,"orden":0},{"Partido":"FUERZA SOCIAL POR MÉXICO","Votos":3,"Porcentaje":0.7634,"orden":0},{"Partido":"CANDIDATO INDEPENDIENTE","Votos":28,"Porcentaje":7.1247,"orden":0},{"Partido":"PAC","Votos":11,"Porcentaje":2.7990,"orden":0},{"Partido":"PS","Votos":8,"Porcentaje":2.0356,"orden":0},{"Partido":"MORENA","Votos":33,"Porcentaje":8.3969,"orden":0},{"Partido":"NUEVA ALIANZA TLAX","Votos":11,"Porcentaje":2.7990,"orden":0},{"Partido":"ENCUENTRO SOCIAL","Votos":0,"Porcentaje":0.0,"orden":0},{"Partido":"IMPACTO SOCIAL SÍ","Votos":6,"Porcentaje":1.5267,"orden":0}],"resumenVotacion":{"Acumulados":{"total":381,"porcentaje":96.9466},"NoRegistradas":{"total":0,"porcentaje":0.0},"VotosNulos":{"total":12,"porcentaje":3.0534},"Total":393,"Observaciones":null},"estadistica":{"Casilla":"CONTIGUA 01","ParticipacionCiudadana":66.9506,"ListaNominal":587}}]},{"SeccionID":539,"Seccion":"Sección 539","actasContabilizadas":[{"NombreCandidatura":"PAN","Votos":106,"Porcentaje":19.7026,"orden":0},{"NombreCandidatura":"PRI","Votos":18,"Porcentaje":3.3457,"orden":0},{"NombreCandidatura":"PRD","Votos":21,"Porcentaje":3.9033,"orden":0},{"NombreCandidatura":"PT","Votos":109,"Porcentaje":20.2602,"orden":0},{"NombreCandidatura":"VERDE","Votos":67,"Porcentaje":12.4535,"orden":0},{"NombreCandidatura":"MOVIMIENTO CIUDADANO","Votos":69,"Porcentaje":12.8253,"orden":0},{"NombreCandidatura":"PES TLAX","Votos":18,"Porcentaje":3.3457,"orden":0},{"NombreCandidatura":"RSP","Votos":11,"Porcentaje":2.0446,"orden":0},{"NombreCandidatura":"FUERZA SOCIAL POR MÉXICO","Votos":4,"Porcentaje":0.7435,"orden":0},{"NombreCandidatura":"CANDIDATO INDEPENDIENTE","Votos":34,"Porcentaje":6.3197,"orden":0},{"NombreCandidatura":"PAC","Votos":8,"Porcentaje":1.4870,"orden":0},{"NombreCandidatura":"PS","Votos":6,"Porcentaje":1.1152,"orden":0},{"NombreCandidatura":"MORENA","Votos":29,"Porcentaje":5.3903,"orden":0},{"NombreCandidatura":"NUEVA ALIANZA TLAX","Votos":7,"Porcentaje":1.3011,"orden":0},{"NombreCandidatura":"ENCUENTRO SOCIAL","Votos":0,"Porcentaje":0.0,"orden":0},{"NombreCandidatura":"IMPACTO SOCIAL SÍ","Votos":21,"Porcentaje":3.9033,"orden":0}],"resumenVotacion":{"acumulados":{"total":528,"porcentaje":98.1413},"nulos":{"total":10,"porcentaje":1.8587},"noRegistradas":{"total":0,"porcentaje":0.0},"totalVotos":{"total":538}},"detalleVotosCasillas":[{"detalleCasilla":{"Id":"DE4FF84916954BDBA37DF58222DAFA664534BB79C6233FFC7F6CE446E7578E41","Casilla":"CONTIGUA 01","ClaveURL":"contigua1","ViaDigitalizacion":1},"candVotTabla":[{"Partido":"PAN","Votos":106,"Porcentaje":19.7026,"orden":0},{"Partido":"PRI","Votos":18,"Porcentaje":3.3457,"orden":0},{"Partido":"PRD","Votos":21,"Porcentaje":3.9033,"orden":0},{"Partido":"PT","Votos":109,"Porcentaje":20.2602,"orden":0},{"Partido":"VERDE","Votos":67,"Porcentaje":12.4535,"orden":0},{"Partido":"MOVIMIENTO CIUDADANO","Votos":69,"Porcentaje":12.8253,"orden":0},{"Partido":"PES TLAX","Votos":18,"Porcentaje":3.3457,"orden":0},{"Partido":"RSP","Votos":11,"Porcentaje":2.0446,"orden":0},{"Partido":"FUERZA SOCIAL POR MÉXICO","Votos":4,"Porcentaje":0.7435,"orden":0},{"Partido":"CANDIDATO INDEPENDIENTE","Votos":34,"Porcentaje":6.3197,"orden":0},{"Partido":"PAC","Votos":8,"Porcentaje":1.4870,"orden":0},{"Partido":"PS","Votos":6,"Porcentaje":1.1152,"orden":0},{"Partido":"MORENA","Votos":29,"Porcentaje":5.3903,"orden":0},{"Partido":"NUEVA ALIANZA TLAX","Votos":7,"Porcentaje":1.3011,"orden":0},{"Partido":"ENCUENTRO SOCIAL","Votos":0,"Porcentaje":0.0,"orden":0},{"Partido":"IMPACTO SOCIAL SÍ","Votos":21,"Porcentaje":3.9033,"orden":0}],"resumenVotacion":{"Acumulados":{"total":528,"porcentaje":98.1413},"NoRegistradas":{"total":0,"porcentaje":0.0},"VotosNulos":{"total":10,"porcentaje":1.8587},"Total":538,"Observaciones":null},"estadistica":{"Casilla":"CONTIGUA 01","ParticipacionCiudadana":74.9304,"ListaNominal":718}}]},{"SeccionID":540,"Seccion":"Sección 540","actasContabilizadas":[{"NombreCandidatura":"PAN","Votos":275,"Porcentaje":15.3803,"orden":0},{"NombreCandidatura":"PRI","Votos":108,"Porcentaje":6.0403,"orden":0},{"NombreCandidatura":"PRD","Votos":89,"Porcentaje":4.9776,"orden":0},{"NombreCandidatura":"PT","Votos":359,"Porcentaje":20.0783,"orden":0},{"NombreCandidatura":"VERDE","Votos":114,"Porcentaje":6.3758,"orden":0},{"NombreCandidatura":"MOVIMIENTO CIUDADANO","Votos":211,"Porcentaje":11.8009,"orden":0},{"NombreCandidatura":"PES TLAX","Votos":94,"Porcentaje":5.2573,"orden":0},{"NombreCandidatura":"RSP","Votos":68,"Porcentaje":3.8031,"orden":0},{"NombreCandidatura":"FUERZA SOCIAL POR MÉXICO","Votos":12,"Porcentaje":0.6711,"orden":0},{"NombreCandidatura":"CANDIDATO INDEPENDIENTE","Votos":158,"Porcentaje":8.8367,"orden":0},{"NombreCandidatura":"PAC","Votos":31,"Porcentaje":1.7338,"orden":0},{"NombreCandidatura":"PS","Votos":43,"Porcentaje":2.4049,"orden":0},{"NombreCandidatura":"MORENA","Votos":85,"Porcentaje":4.7539,"orden":0},{"NombreCandidatura":"NUEVA ALIANZA TLAX","Votos":58,"Porcentaje":3.2438,"orden":0},{"NombreCandidatura":"ENCUENTRO SOCIAL","Votos":1,"Porcentaje":0.0559,"orden":0},{"NombreCandidatura":"IMPACTO SOCIAL SÍ","Votos":46,"Porcentaje":2.5727,"orden":0}],"resumenVotacion":{"acumulados":{"total":1752,"porcentaje":97.9866},"nulos":{"total":36,"porcentaje":2.0134},"noRegistradas":{"total":0,"porcentaje":0.0},"totalVotos":{"total":1788}},"detalleVotosCasillas":[{"detalleCasilla":{"Id":"432CBB1783091FFFEC84D5A253E61E0B349FF2090DD07BDACD2FB2915BD8AD86","Casilla":"CONTIGUA 04","ClaveURL":"contigua4","ViaDigitalizacion":1},"candVotTabla":[{"Partido":"PAN","Votos":84,"Porcentaje":17.5732,"orden":0},{"Partido":"PRI","Votos":28,"Porcentaje":5.8577,"orden":0},{"Partido":"PRD","Votos":16,"Porcentaje":3.3473,"orden":0},{"Partido":"PT","Votos":84,"Porcentaje":17.5732,"orden":0},{"Partido":"VERDE","Votos":31,"Porcentaje":6.4854,"orden":0},{"Partido":"MOVIMIENTO CIUDADANO","Votos":65,"Porcentaje":13.5983,"orden":0},{"Partido":"PES TLAX","Votos":44,"Porcentaje":9.2050,"orden":0},{"Partido":"RSP","Votos":13,"Porcentaje":2.7197,"orden":0},{"Partido":"FUERZA SOCIAL POR MÉXICO","Votos":3,"Porcentaje":0.6276,"orden":0},{"Partido":"CANDIDATO INDEPENDIENTE","Votos":43,"Porcentaje":8.9958,"orden":0},{"Partido":"PAC","Votos":6,"Porcentaje":1.2552,"orden":0},{"Partido":"PS","Votos":12,"Porcentaje":2.5105,"orden":0},{"Partido":"MORENA","Votos":18,"Porcentaje":3.7657,"orden":0},{"Partido":"NUEVA ALIANZA TLAX","Votos":9,"Porcentaje":1.8828,"orden":0},{"Partido":"ENCUENTRO SOCIAL","Votos":0,"Porcentaje":0.0,"orden":0},{"Partido":"IMPACTO SOCIAL SÍ","Votos":14,"Porcentaje":2.9289,"orden":0}],"resumenVotacion":{"Acumulados":{"total":470,"porcentaje":98.3264},"NoRegistradas":{"total":0,"porcentaje":0.0},"VotosNulos":{"total":8,"porcentaje":1.6736},"Total":478,"Observaciones":null},"estadistica":{"Casilla":"CONTIGUA 04","ParticipacionCiudadana":69.8830,"ListaNominal":684}},{"detalleCasilla":{"Id":"B9828D83FA6F3C404D68E60BB90E3F027A7FC4E9E7E202004501DADD79A92626","Casilla":"CONTIGUA 03","ClaveURL":"contigua3","ViaDigitalizacion":1},"candVotTabla":[{"Partido":"PAN","Votos":12,"Porcentaje":3.3994,"orden":0},{"Partido":"PRI","Votos":24,"Porcentaje":6.7989,"orden":0},{"Partido":"PRD","Votos":22,"Porcentaje":6.2323,"orden":0},{"Partido":"PT","Votos":78,"Porcentaje":22.0963,"orden":0},{"Partido":"VERDE","Votos":32,"Porcentaje":9.0652,"orden":0},{"Partido":"MOVIMIENTO CIUDADANO","Votos":36,"Porcentaje":10.1983,"orden":0},{"Partido":"PES TLAX","Votos":20,"Porcentaje":5.6657,"orden":0},{"Partido":"RSP","Votos":26,"Porcentaje":7.3654,"orden":0},{"Partido":"FUERZA SOCIAL POR MÉXICO","Votos":4,"Porcentaje":1.1331,"orden":0},{"Partido":"CANDIDATO INDEPENDIENTE","Votos":28,"Porcentaje":7.9320,"orden":0},{"Partido":"PAC","Votos":6,"Porcentaje":1.6997,"orden":0},{"Partido":"PS","Votos":9,"Porcentaje":2.5496,"orden":0},{"Partido":"MORENA","Votos":14,"Porcentaje":3.9660,"orden":0},{"Partido":"NUEVA ALIANZA TLAX","Votos":24,"Porcentaje":6.7989,"orden":0},{"Partido":"ENCUENTRO SOCIAL","Votos":1,"Porcentaje":0.2833,"orden":0},{"Partido":"IMPACTO SOCIAL SÍ","Votos":8,"Porcentaje":2.2663,"orden":0}],"resumenVotacion":{"Acumulados":{"total":344,"porcentaje":97.4504},"NoRegistradas":{"total":0,"porcentaje":0.0},"VotosNulos":{"total":9,"porcentaje":2.5496},"Total":353,"Observaciones":null},"estadistica":{"Casilla":"CONTIGUA 03","ParticipacionCiudadana":51.5328,"ListaNominal":685}},{"detalleCasilla":{"Id":"CB822013D641AE18709F215FEE01647C4B6B406C8E226346629E583D60D2AA07","Casilla":"CONTIGUA 02","ClaveURL":"contigua2","ViaDigitalizacion":1},"candVotTabla":[{"Partido":"PAN","Votos":95,"Porcentaje":18.9621,"orden":0},{"Partido":"PRI","Votos":26,"Porcentaje":5.1896,"orden":0},{"Partido":"PRD","Votos":23,"Porcentaje":4.5908,"orden":0},{"Partido":"PT","Votos":105,"Porcentaje":20.9581,"orden":0},{"Partido":"VERDE","Votos":22,"Porcentaje":4.3912,"orden":0},{"Partido":"MOVIMIENTO CIUDADANO","Votos":62,"Porcentaje":12.3752,"orden":0},{"Partido":"PES TLAX","Votos":22,"Porcentaje":4.3912,"orden":0},{"Partido":"RSP","Votos":15,"Porcentaje":2.9940,"orden":0},{"Partido":"FUERZA SOCIAL POR MÉXICO","Votos":3,"Porcentaje":0.5988,"orden":0},{"Partido":"CANDIDATO INDEPENDIENTE","Votos":34,"Porcentaje":6.7864,"orden":0},{"Partido":"PAC","Votos":10,"Porcentaje":1.9960,"orden":0},{"Partido":"PS","Votos":14,"Porcentaje":2.7944,"orden":0},{"Partido":"MORENA","Votos":32,"Porcentaje":6.3872,"orden":0},{"Partido":"NUEVA ALIANZA TLAX","Votos":15,"Porcentaje":2.9940,"orden":0},{"Partido":"ENCUENTRO SOCIAL","Votos":0,"Porcentaje":0.0,"orden":0},{"Partido":"IMPACTO SOCIAL SÍ","Votos":15,"Porcentaje":2.9940,"orden":0}],"resumenVotacion":{"Acumulados":{"total":493,"porcentaje":98.4032},"NoRegistradas":{"total":0,"porcentaje":0.0},"VotosNulos":{"total":8,"porcentaje":1.5968},"Total":501,"Observaciones":null},"estadistica":{"Casilla":"CONTIGUA 02","ParticipacionCiudadana":73.1387,"ListaNominal":685}},{"detalleCasilla":{"Id":"EE0EFE53DEDE37803DB610D42DEE38FD59EC129D1C55DA0E9825E6A73D4B4DA3","Casilla":"CONTIGUA 01","ClaveURL":"contigua1","ViaDigitalizacion":1},"candVotTabla":[{"Partido":"PAN","Votos":84,"Porcentaje":18.4211,"orden":0},{"Partido":"PRI","Votos":30,"Porcentaje":6.5789,"orden":0},{"Partido":"PRD","Votos":28,"Porcentaje":6.1404,"orden":0},{"Partido":"PT","Votos":92,"Porcentaje":20.1754,"orden":0},{"Partido":"VERDE","Votos":29,"Porcentaje":6.3596,"orden":0},{"Partido":"MOVIMIENTO CIUDADANO","Votos":48,"Porcentaje":10.5263,"orden":0},{"Partido":"PES TLAX","Votos":8,"Porcentaje":1.7544,"orden":0},{"Partido":"RSP","Votos":14,"Porcentaje":3.0702,"orden":0},{"Partido":"FUERZA SOCIAL POR MÉXICO","Votos":2,"Porcentaje":0.4386,"orden":0},{"Partido":"CANDIDATO INDEPENDIENTE","Votos":53,"Porcentaje":11.6228,"orden":0},{"Partido":"PAC","Votos":9,"Porcentaje":1.9737,"orden":0},{"Partido":"PS","Votos":8,"Porcentaje":1.7544,"orden":0},{"Partido":"MORENA","Votos":21,"Porcentaje":4.6053,"orden":0},{"Partido":"NUEVA ALIANZA TLAX","Votos":10,"Porcentaje":2.1930,"orden":0},{"Partido":"ENCUENTRO SOCIAL","Votos":0,"Porcentaje":0.0,"orden":0},{"Partido":"IMPACTO SOCIAL SÍ","Votos":9,"Porcentaje":1.9737,"orden":0}],"resumenVotacion":{"Acumulados":{"total":445,"porcentaje":97.5877},"NoRegistradas":{"total":0,"porcentaje":0.0},"VotosNulos":{"total":11,"porcentaje":2.4123},"Total":456,"Observaciones":null},"estadistica":{"Casilla":"CONTIGUA 01","ParticipacionCiudadana":66.5693,"ListaNominal":685}}]},{"SeccionID":541,"Seccion":"Sección 541","actasContabilizadas":[{"NombreCandidatura":"PAN","Votos":254,"Porcentaje":17.6022,"orden":0},{"NombreCandidatura":"PRI","Votos":73,"Porcentaje":5.0589,"orden":0},{"NombreCandidatura":"PRD","Votos":51,"Porcentaje":3.5343,"orden":0},{"NombreCandidatura":"PT","Votos":206,"Porcentaje":14.2758,"orden":0},{"NombreCandidatura":"VERDE","Votos":220,"Porcentaje":15.2460,"orden":0},{"NombreCandidatura":"MOVIMIENTO CIUDADANO","Votos":128,"Porcentaje":8.8704,"orden":0},{"NombreCandidatura":"PES TLAX","Votos":46,"Porcentaje":3.1878,"orden":0},{"NombreCandidatura":"RSP","Votos":78,"Porcentaje":5.4054,"orden":0},{"NombreCandidatura":"FUERZA SOCIAL POR MÉXICO","Votos":9,"Porcentaje":0.6237,"orden":0},{"NombreCandidatura":"CANDIDATO INDEPENDIENTE","Votos":88,"Porcentaje":6.0984,"orden":0},{"NombreCandidatura":"PAC","Votos":31,"Porcentaje":2.1483,"orden":0},{"NombreCandidatura":"PS","Votos":53,"Porcentaje":3.6729,"orden":0},{"NombreCandidatura":"MORENA","Votos":117,"Porcentaje":8.1081,"orden":0},{"NombreCandidatura":"NUEVA ALIANZA TLAX","Votos":9,"Porcentaje":0.6237,"orden":0},{"NombreCandidatura":"ENCUENTRO SOCIAL","Votos":0,"Porcentaje":0.0,"orden":0},{"NombreCandidatura":"IMPACTO SOCIAL SÍ","Votos":34,"Porcentaje":2.3562,"orden":0}],"resumenVotacion":{"acumulados":{"total":1397,"porcentaje":96.8122},"nulos":{"total":46,"porcentaje":3.1878},"noRegistradas":{"total":0,"porcentaje":0.0},"totalVotos":{"total":1443}},"detalleVotosCasillas":[{"detalleCasilla":{"Id":"154018F957B7603339A35A179F18521C6AECD70F287A4EC7330E1A6BC3FAF752","Casilla":"BÁSICA 01","ClaveURL":"basica1","ViaDigitalizacion":1},"candVotTabla":[{"Partido":"PAN","Votos":62,"Porcentaje":12.6273,"orden":0},{"Partido":"PRI","Votos":19,"Porcentaje":3.8697,"orden":0},{"Partido":"PRD","Votos":21,"Porcentaje":4.2770,"orden":0},{"Partido":"PT","Votos":83,"Porcentaje":16.9043,"orden":0},{"Partido":"VERDE","Votos":73,"Porcentaje":14.8676,"orden":0},{"Partido":"MOVIMIENTO CIUDADANO","Votos":54,"Porcentaje":10.9980,"orden":0},{"Partido":"PES TLAX","Votos":17,"Porcentaje":3.4623,"orden":0},{"Partido":"RSP","Votos":16,"Porcentaje":3.2587,"orden":0},{"Partido":"FUERZA SOCIAL POR MÉXICO","Votos":0,"Porcentaje":0.0,"orden":0},{"Partido":"CANDIDATO INDEPENDIENTE","Votos":37,"Porcentaje":7.5356,"orden":0},{"Partido":"PAC","Votos":14,"Porcentaje":2.8513,"orden":0},{"Partido":"PS","Votos":15,"Porcentaje":3.0550,"orden":0},{"Partido":"MORENA","Votos":38,"Porcentaje":7.7393,"orden":0},{"Partido":"NUEVA ALIANZA TLAX","Votos":3,"Porcentaje":0.6110,"orden":0},{"Partido":"ENCUENTRO SOCIAL","Votos":0,"Porcentaje":0.0,"orden":0},{"Partido":"IMPACTO SOCIAL SÍ","Votos":19,"Porcentaje":3.8697,"orden":0}],"resumenVotacion":{"Acumulados":{"total":471,"porcentaje":95.9267},"NoRegistradas":{"total":0,"porcentaje":0.0},"VotosNulos":{"total":20,"porcentaje":4.0733},"Total":491,"Observaciones":null},"estadistica":{"Casilla":"BÁSICA 01","ParticipacionCiudadana":69.8435,"ListaNominal":703}},{"detalleCasilla":{"Id":"54D06802A2E10100FB45DF31C52871696F505C52009CA9A50333A31132AB21AB","Casilla":"CONTIGUA 02","ClaveURL":"contigua2","ViaDigitalizacion":1},"candVotTabla":[{"Partido":"PAN","Votos":105,"Porcentaje":22.9759,"orden":0},{"Partido":"PRI","Votos":25,"Porcentaje":5.4705,"orden":0},{"Partido":"PRD","Votos":8,"Porcentaje":1.7505,"orden":0},{"Partido":"PT","Votos":64,"Porcentaje":14.0044,"orden":0},{"Partido":"VERDE","Votos":54,"Porcentaje":11.8162,"orden":0},{"Partido":"MOVIMIENTO CIUDADANO","Votos":33,"Porcentaje":7.2210,"orden":0},{"Partido":"PES TLAX","Votos":11,"Porcentaje":2.4070,"orden":0},{"Partido":"RSP","Votos":41,"Porcentaje":8.9716,"orden":0},{"Partido":"FUERZA SOCIAL POR MÉXICO","Votos":4,"Porcentaje":0.8753,"orden":0},{"Partido":"CANDIDATO INDEPENDIENTE","Votos":31,"Porcentaje":6.7834,"orden":0},{"Partido":"PAC","Votos":11,"Porcentaje":2.4070,"orden":0},{"Partido":"PS","Votos":17,"Porcentaje":3.7199,"orden":0},{"Partido":"MORENA","Votos":31,"Porcentaje":6.7834,"orden":0},{"Partido":"NUEVA ALIANZA TLAX","Votos":2,"Porcentaje":0.4376,"orden":0},{"Partido":"ENCUENTRO SOCIAL","Votos":0,"Porcentaje":0.0,"orden":0},{"Partido":"IMPACTO SOCIAL SÍ","Votos":8,"Porcentaje":1.7505,"orden":0}],"resumenVotacion":{"Acumulados":{"total":445,"porcentaje":97.3742},"NoRegistradas":{"total":0,"porcentaje":0.0},"VotosNulos":{"total":12,"porcentaje":2.6258},"Total":457,"Observaciones":null},"estadistica":{"Casilla":"CONTIGUA 02","ParticipacionCiudadana":65.0071,"ListaNominal":703}},{"detalleCasilla":{"Id":"CD67BC73271803ADE4135FA722BC66F699EC77E63B39583699AAC9AF95B1BCEC","Casilla":"CONTIGUA 03","ClaveURL":"contigua3","ViaDigitalizacion":1},"candVotTabla":[{"Partido":"PAN","Votos":87,"Porcentaje":17.5758,"orden":0},{"Partido":"PRI","Votos":29,"Porcentaje":5.8586,"orden":0},{"Partido":"PRD","Votos":22,"Porcentaje":4.4444,"orden":0},{"Partido":"PT","Votos":59,"Porcentaje":11.9192,"orden":0},{"Partido":"VERDE","Votos":93,"Porcentaje":18.7879,"orden":0},{"Partido":"MOVIMIENTO CIUDADANO","Votos":41,"Porcentaje":8.2828,"orden":0},{"Partido":"PES TLAX","Votos":18,"Porcentaje":3.6364,"orden":0},{"Partido":"RSP","Votos":21,"Porcentaje":4.2424,"orden":0},{"Partido":"FUERZA SOCIAL POR MÉXICO","Votos":5,"Porcentaje":1.0101,"orden":0},{"Partido":"CANDIDATO INDEPENDIENTE","Votos":20,"Porcentaje":4.0404,"orden":0},{"Partido":"PAC","Votos":6,"Porcentaje":1.2121,"orden":0},{"Partido":"PS","Votos":21,"Porcentaje":4.2424,"orden":0},{"Partido":"MORENA","Votos":48,"Porcentaje":9.6970,"orden":0},{"Partido":"NUEVA ALIANZA TLAX","Votos":4,"Porcentaje":0.8081,"orden":0},{"Partido":"ENCUENTRO SOCIAL","Votos":0,"Porcentaje":0.0,"orden":0},{"Partido":"IMPACTO SOCIAL SÍ","Votos":7,"Porcentaje":1.4141,"orden":0}],"resumenVotacion":{"Acumulados":{"total":481,"porcentaje":97.1717},"NoRegistradas":{"total":0,"porcentaje":0.0},"VotosNulos":{"total":14,"porcentaje":2.8283},"Total":495,"Observaciones":null},"estadistica":{"Casilla":"CONTIGUA 03","ParticipacionCiudadana":70.4125,"ListaNominal":703}}]},{"SeccionID":542,"Seccion":"Sección 542","actasContabilizadas":[{"NombreCandidatura":"PAN","Votos":192,"Porcentaje":11.4627,"orden":0},{"NombreCandidatura":"PRI","Votos":65,"Porcentaje":3.8806,"orden":0},{"NombreCandidatura":"PRD","Votos":40,"Porcentaje":2.3881,"orden":0},{"NombreCandidatura":"PT","Votos":288,"Porcentaje":17.1940,"orden":0},{"NombreCandidatura":"VERDE","Votos":67,"Porcentaje":4.0,"orden":0},{"NombreCandidatura":"MOVIMIENTO CIUDADANO","Votos":492,"Porcentaje":29.3731,"orden":0},{"NombreCandidatura":"PES TLAX","Votos":22,"Porcentaje":1.3134,"orden":0},{"NombreCandidatura":"RSP","Votos":84,"Porcentaje":5.0149,"orden":0},{"NombreCandidatura":"FUERZA SOCIAL POR MÉXICO","Votos":45,"Porcentaje":2.6866,"orden":0},{"NombreCandidatura":"CANDIDATO INDEPENDIENTE","Votos":104,"Porcentaje":6.2090,"orden":0},{"NombreCandidatura":"PAC","Votos":25,"Porcentaje":1.4925,"orden":0},{"NombreCandidatura":"PS","Votos":56,"Porcentaje":3.3433,"orden":0},{"NombreCandidatura":"MORENA","Votos":73,"Porcentaje":4.3582,"orden":0},{"NombreCandidatura":"NUEVA ALIANZA TLAX","Votos":25,"Porcentaje":1.4925,"orden":0},{"NombreCandidatura":"ENCUENTRO SOCIAL","Votos":8,"Porcentaje":0.4776,"orden":0},{"NombreCandidatura":"IMPACTO SOCIAL SÍ","Votos":50,"Porcentaje":2.9851,"orden":0}],"resumenVotacion":{"acumulados":{"total":1637,"porcentaje":97.7313},"nulos":{"total":38,"porcentaje":2.2687},"noRegistradas":{"total":1,"porcentaje":0.0597},"totalVotos":{"total":1675}},"detalleVotosCasillas":[{"detalleCasilla":{"Id":"32B03186BAE973B6A20D4830350386B6DB1552EF8867766126DC58B176407F96","Casilla":"CONTIGUA 03","ClaveURL":"contigua3","ViaDigitalizacion":1},"candVotTabla":[{"Partido":"PAN","Votos":50,"Porcentaje":12.1065,"orden":0},{"Partido":"PRI","Votos":13,"Porcentaje":3.1477,"orden":0},{"Partido":"PRD","Votos":8,"Porcentaje":1.9370,"orden":0},{"Partido":"PT","Votos":74,"Porcentaje":17.9177,"orden":0},{"Partido":"VERDE","Votos":26,"Porcentaje":6.2954,"orden":0},{"Partido":"MOVIMIENTO CIUDADANO","Votos":119,"Porcentaje":28.8136,"orden":0},{"Partido":"PES TLAX","Votos":5,"Porcentaje":1.2107,"orden":0},{"Partido":"RSP","Votos":28,"Porcentaje":6.7797,"orden":0},{"Partido":"FUERZA SOCIAL POR MÉXICO","Votos":2,"Porcentaje":0.4843,"orden":0},{"Partido":"CANDIDATO INDEPENDIENTE","Votos":29,"Porcentaje":7.0218,"orden":0},{"Partido":"PAC","Votos":3,"Porcentaje":0.7264,"orden":0},{"Partido":"PS","Votos":17,"Porcentaje":4.1162,"orden":0},{"Partido":"MORENA","Votos":17,"Porcentaje":4.1162,"orden":0},{"Partido":"NUEVA ALIANZA TLAX","Votos":5,"Porcentaje":1.2107,"orden":0},{"Partido":"ENCUENTRO SOCIAL","Votos":2,"Porcentaje":0.4843,"orden":0},{"Partido":"IMPACTO SOCIAL SÍ","Votos":6,"Porcentaje":1.4528,"orden":0}],"resumenVotacion":{"Acumulados":{"total":404,"porcentaje":97.8208},"NoRegistradas":{"total":0,"porcentaje":0.0},"VotosNulos":{"total":9,"porcentaje":2.1792},"Total":413,"Observaciones":null},"estadistica":{"Casilla":"CONTIGUA 03","ParticipacionCiudadana":63.9319,"ListaNominal":646}},{"detalleCasilla":{"Id":"5A3944E3FD35E4AB8979566C4ED5269A38A74BBD9929CD3C1F6193A1A4A149E2","Casilla":"CONTIGUA 02","ClaveURL":"contigua2","ViaDigitalizacion":1},"candVotTabla":[{"Partido":"PAN","Votos":33,"Porcentaje":8.0882,"orden":0},{"Partido":"PRI","Votos":12,"Porcentaje":2.9412,"orden":0},{"Partido":"PRD","Votos":5,"Porcentaje":1.2255,"orden":0},{"Partido":"PT","Votos":75,"Porcentaje":18.3824,"orden":0},{"Partido":"VERDE","Votos":16,"Porcentaje":3.9216,"orden":0},{"Partido":"MOVIMIENTO CIUDADANO","Votos":135,"Porcentaje":33.0882,"orden":0},{"Partido":"PES TLAX","Votos":8,"Porcentaje":1.9608,"orden":0},{"Partido":"RSP","Votos":17,"Porcentaje":4.1667,"orden":0},{"Partido":"FUERZA SOCIAL POR MÉXICO","Votos":5,"Porcentaje":1.2255,"orden":0},{"Partido":"CANDIDATO INDEPENDIENTE","Votos":30,"Porcentaje":7.3529,"orden":0},{"Partido":"PAC","Votos":7,"Porcentaje":1.7157,"orden":0},{"Partido":"PS","Votos":17,"Porcentaje":4.1667,"orden":0},{"Partido":"MORENA","Votos":21,"Porcentaje":5.1471,"orden":0},{"Partido":"NUEVA ALIANZA TLAX","Votos":4,"Porcentaje":0.9804,"orden":0},{"Partido":"ENCUENTRO SOCIAL","Votos":0,"Porcentaje":0.0,"orden":0},{"Partido":"IMPACTO SOCIAL SÍ","Votos":15,"Porcentaje":3.6765,"orden":0}],"resumenVotacion":{"Acumulados":{"total":400,"porcentaje":98.0392},"NoRegistradas":{"total":0,"porcentaje":0.0},"VotosNulos":{"total":8,"porcentaje":1.9608},"Total":408,"Observaciones":null},"estadistica":{"Casilla":"CONTIGUA 02","ParticipacionCiudadana":63.1579,"ListaNominal":646}},{"detalleCasilla":{"Id":"984B28A29A7E29A7CAFA927990464E0F641284E977F735DBCB5CE17CBA3D90D3","Casilla":"CONTIGUA 01","ClaveURL":"contigua1","ViaDigitalizacion":1},"candVotTabla":[{"Partido":"PAN","Votos":62,"Porcentaje":14.0909,"orden":0},{"Partido":"PRI","Votos":19,"Porcentaje":4.3182,"orden":0},{"Partido":"PRD","Votos":17,"Porcentaje":3.8636,"orden":0},{"Partido":"PT","Votos":81,"Porcentaje":18.4091,"orden":0},{"Partido":"VERDE","Votos":16,"Porcentaje":3.6364,"orden":0},{"Partido":"MOVIMIENTO CIUDADANO","Votos":113,"Porcentaje":25.6818,"orden":0},{"Partido":"PES TLAX","Votos":4,"Porcentaje":0.9091,"orden":0},{"Partido":"RSP","Votos":18,"Porcentaje":4.0909,"orden":0},{"Partido":"FUERZA SOCIAL POR MÉXICO","Votos":2,"Porcentaje":0.4545,"orden":0},{"Partido":"CANDIDATO INDEPENDIENTE","Votos":45,"Porcentaje":10.2273,"orden":0},{"Partido":"PAC","Votos":6,"Porcentaje":1.3636,"orden":0},{"Partido":"PS","Votos":11,"Porcentaje":2.5,"orden":0},{"Partido":"MORENA","Votos":17,"Porcentaje":3.8636,"orden":0},{"Partido":"NUEVA ALIANZA TLAX","Votos":6,"Porcentaje":1.3636,"orden":0},{"Partido":"ENCUENTRO SOCIAL","Votos":1,"Porcentaje":0.2273,"orden":0},{"Partido":"IMPACTO SOCIAL SÍ","Votos":11,"Porcentaje":2.5,"orden":0}],"resumenVotacion":{"Acumulados":{"total":429,"porcentaje":97.5},"NoRegistradas":{"total":1,"porcentaje":0.2273},"VotosNulos":{"total":10,"porcentaje":2.2727},"Total":440,"Observaciones":null},"estadistica":{"Casilla":"CONTIGUA 01","ParticipacionCiudadana":68.0062,"ListaNominal":647}},{"detalleCasilla":{"Id":"F1CB9A7EDA7EAD4449DFB4CDD8B35968B32EBC8379F3BB52B60A76646A519843","Casilla":"BÁSICA 01","ClaveURL":"basica1","ViaDigitalizacion":1},"candVotTabla":[{"Partido":"PAN","Votos":47,"Porcentaje":11.3527,"orden":0},{"Partido":"PRI","Votos":21,"Porcentaje":5.0725,"orden":0},{"Partido":"PRD","Votos":10,"Porcentaje":2.4155,"orden":0},{"Partido":"PT","Votos":58,"Porcentaje":14.0097,"orden":0},{"Partido":"VERDE","Votos":9,"Porcentaje":2.1739,"orden":0},{"Partido":"MOVIMIENTO CIUDADANO","Votos":125,"Porcentaje":30.1932,"orden":0},{"Partido":"PES TLAX","Votos":5,"Porcentaje":1.2077,"orden":0},{"Partido":"RSP","Votos":21,"Porcentaje":5.0725,"orden":0},{"Partido":"FUERZA SOCIAL POR MÉXICO","Votos":36,"Porcentaje":8.6957,"orden":0},{"Partido":"CANDIDATO INDEPENDIENTE","Votos":0,"Porcentaje":0.0,"orden":0},{"Partido":"PAC","Votos":9,"Porcentaje":2.1739,"orden":0},{"Partido":"PS","Votos":11,"Porcentaje":2.6570,"orden":0},{"Partido":"MORENA","Votos":18,"Porcentaje":4.3478,"orden":0},{"Partido":"NUEVA ALIANZA TLAX","Votos":10,"Porcentaje":2.4155,"orden":0},{"Partido":"ENCUENTRO SOCIAL","Votos":5,"Porcentaje":1.2077,"orden":0},{"Partido":"IMPACTO SOCIAL SÍ","Votos":18,"Porcentaje":4.3478,"orden":0}],"resumenVotacion":{"Acumulados":{"total":403,"porcentaje":97.3430},"NoRegistradas":{"total":0,"porcentaje":0.0},"VotosNulos":{"total":11,"porcentaje":2.6570},"Total":414,"Observaciones":"Todos ilegibles o sin dato"},"estadistica":{"Casilla":"BÁSICA 01","ParticipacionCiudadana":63.9876,"ListaNominal":647}}]},{"SeccionID":543,"Seccion":"Sección 543","actasContabilizadas":[{"NombreCandidatura":"PAN","Votos":243,"Porcentaje":15.7588,"orden":0},{"NombreCandidatura":"PRI","Votos":100,"Porcentaje":6.4851,"orden":0},{"NombreCandidatura":"PRD","Votos":34,"Porcentaje":2.2049,"orden":0},{"NombreCandidatura":"PT","Votos":225,"Porcentaje":14.5914,"orden":0},{"NombreCandidatura":"VERDE","Votos":99,"Porcentaje":6.4202,"orden":0},{"NombreCandidatura":"MOVIMIENTO CIUDADANO","Votos":197,"Porcentaje":12.7756,"orden":0},{"NombreCandidatura":"PES TLAX","Votos":40,"Porcentaje":2.5940,"orden":0},{"NombreCandidatura":"RSP","Votos":69,"Porcentaje":4.4747,"orden":0},{"NombreCandidatura":"FUERZA SOCIAL POR MÉXICO","Votos":11,"Porcentaje":0.7134,"orden":0},{"NombreCandidatura":"CANDIDATO INDEPENDIENTE","Votos":248,"Porcentaje":16.0830,"orden":0},{"NombreCandidatura":"PAC","Votos":41,"Porcentaje":2.6589,"orden":0},{"NombreCandidatura":"PS","Votos":11,"Porcentaje":0.7134,"orden":0},{"NombreCandidatura":"MORENA","Votos":74,"Porcentaje":4.7990,"orden":0},{"NombreCandidatura":"NUEVA ALIANZA TLAX","Votos":14,"Porcentaje":0.9079,"orden":0},{"NombreCandidatura":"ENCUENTRO SOCIAL","Votos":2,"Porcentaje":0.1297,"orden":0},{"NombreCandidatura":"IMPACTO SOCIAL SÍ","Votos":97,"Porcentaje":6.2905,"orden":0}],"resumenVotacion":{"acumulados":{"total":1505,"porcentaje":97.6005},"nulos":{"total":37,"porcentaje":2.3995},"noRegistradas":{"total":0,"porcentaje":0.0},"totalVotos":{"total":1542}},"detalleVotosCasillas":[{"detalleCasilla":{"Id":"27CDCFD6DA1594F6A2DF48AB67412EE655C411A199833E763D8CF64A3204075E","Casilla":"CONTIGUA 01","ClaveURL":"contigua1","ViaDigitalizacion":1},"candVotTabla":[{"Partido":"PAN","Votos":95,"Porcentaje":18.3752,"orden":0},{"Partido":"PRI","Votos":29,"Porcentaje":5.6093,"orden":0},{"Partido":"PRD","Votos":13,"Porcentaje":2.5145,"orden":0},{"Partido":"PT","Votos":72,"Porcentaje":13.9265,"orden":0},{"Partido":"VERDE","Votos":38,"Porcentaje":7.3501,"orden":0},{"Partido":"MOVIMIENTO CIUDADANO","Votos":61,"Porcentaje":11.7988,"orden":0},{"Partido":"PES TLAX","Votos":10,"Porcentaje":1.9342,"orden":0},{"Partido":"RSP","Votos":13,"Porcentaje":2.5145,"orden":0},{"Partido":"FUERZA SOCIAL POR MÉXICO","Votos":1,"Porcentaje":0.1934,"orden":0},{"Partido":"CANDIDATO INDEPENDIENTE","Votos":96,"Porcentaje":18.5687,"orden":0},{"Partido":"PAC","Votos":16,"Porcentaje":3.0948,"orden":0},{"Partido":"PS","Votos":6,"Porcentaje":1.1605,"orden":0},{"Partido":"MORENA","Votos":20,"Porcentaje":3.8685,"orden":0},{"Partido":"NUEVA ALIANZA TLAX","Votos":3,"Porcentaje":0.5803,"orden":0},{"Partido":"ENCUENTRO SOCIAL","Votos":1,"Porcentaje":0.1934,"orden":0},{"Partido":"IMPACTO SOCIAL SÍ","Votos":27,"Porcentaje":5.2224,"orden":0}],"resumenVotacion":{"Acumulados":{"total":501,"porcentaje":96.9052},"NoRegistradas":{"total":0,"porcentaje":0.0},"VotosNulos":{"total":16,"porcentaje":3.0948},"Total":517,"Observaciones":null},"estadistica":{"Casilla":"CONTIGUA 01","ParticipacionCiudadana":70.7250,"ListaNominal":731}},{"detalleCasilla":{"Id":"344AF46E51B3D6593C45FD4A3C5DB8F9F0617210F6DF30BBA8865E31E1F4B509","Casilla":"CONTIGUA 02","ClaveURL":"contigua2","ViaDigitalizacion":1},"candVotTabla":[{"Partido":"PAN","Votos":82,"Porcentaje":16.3347,"orden":0},{"Partido":"PRI","Votos":46,"Porcentaje":9.1633,"orden":0},{"Partido":"PRD","Votos":8,"Porcentaje":1.5936,"orden":0},{"Partido":"PT","Votos":74,"Porcentaje":14.7410,"orden":0},{"Partido":"VERDE","Votos":37,"Porcentaje":7.3705,"orden":0},{"Partido":"MOVIMIENTO CIUDADANO","Votos":42,"Porcentaje":8.3665,"orden":0},{"Partido":"PES TLAX","Votos":11,"Porcentaje":2.1912,"orden":0},{"Partido":"RSP","Votos":23,"Porcentaje":4.5817,"orden":0},{"Partido":"FUERZA SOCIAL POR MÉXICO","Votos":7,"Porcentaje":1.3944,"orden":0},{"Partido":"CANDIDATO INDEPENDIENTE","Votos":77,"Porcentaje":15.3386,"orden":0},{"Partido":"PAC","Votos":11,"Porcentaje":2.1912,"orden":0},{"Partido":"PS","Votos":3,"Porcentaje":0.5976,"orden":0},{"Partido":"MORENA","Votos":27,"Porcentaje":5.3785,"orden":0},{"Partido":"NUEVA ALIANZA TLAX","Votos":3,"Porcentaje":0.5976,"orden":0},{"Partido":"ENCUENTRO SOCIAL","Votos":0,"Porcentaje":0.0,"orden":0},{"Partido":"IMPACTO SOCIAL SÍ","Votos":37,"Porcentaje":7.3705,"orden":0}],"resumenVotacion":{"Acumulados":{"total":488,"porcentaje":97.2112},"NoRegistradas":{"total":0,"porcentaje":0.0},"VotosNulos":{"total":14,"porcentaje":2.7888},"Total":502,"Observaciones":"Todos ilegibles o sin dato"},"estadistica":{"Casilla":"CONTIGUA 02","ParticipacionCiudadana":68.7671,"ListaNominal":730}},{"detalleCasilla":{"Id":"A3C88E209406F60D7813DB9F220A62D5DF53A7B3A27CAC3A132380B329CB26E4","Casilla":"BÁSICA 01","ClaveURL":"basica1","ViaDigitalizacion":1},"candVotTabla":[{"Partido":"PAN","Votos":66,"Porcentaje":12.6195,"orden":0},{"Partido":"PRI","Votos":25,"Porcentaje":4.7801,"orden":0},{"Partido":"PRD","Votos":13,"Porcentaje":2.4857,"orden":0},{"Partido":"PT","Votos":79,"Porcentaje":15.1052,"orden":0},{"Partido":"VERDE","Votos":24,"Porcentaje":4.5889,"orden":0},{"Partido":"MOVIMIENTO CIUDADANO","Votos":94,"Porcentaje":17.9732,"orden":0},{"Partido":"PES TLAX","Votos":19,"Porcentaje":3.6329,"orden":0},{"Partido":"RSP","Votos":33,"Porcentaje":6.3098,"orden":0},{"Partido":"FUERZA SOCIAL POR MÉXICO","Votos":3,"Porcentaje":0.5736,"orden":0},{"Partido":"CANDIDATO INDEPENDIENTE","Votos":75,"Porcentaje":14.3403,"orden":0},{"Partido":"PAC","Votos":14,"Porcentaje":2.6769,"orden":0},{"Partido":"PS","Votos":2,"Porcentaje":0.3824,"orden":0},{"Partido":"MORENA","Votos":27,"Porcentaje":5.1625,"orden":0},{"Partido":"NUEVA ALIANZA TLAX","Votos":8,"Porcentaje":1.5296,"orden":0},{"Partido":"ENCUENTRO SOCIAL","Votos":1,"Porcentaje":0.1912,"orden":0},{"Partido":"IMPACTO SOCIAL SÍ","Votos":33,"Porcentaje":6.3098,"orden":0}],"resumenVotacion":{"Acumulados":{"total":516,"porcentaje":98.6616},"NoRegistradas":{"total":0,"porcentaje":0.0},"VotosNulos":{"total":7,"porcentaje":1.3384},"Total":523,"Observaciones":null},"estadistica":{"Casilla":"BÁSICA 01","ParticipacionCiudadana":71.5458,"ListaNominal":731}}]},{"SeccionID":544,"Seccion":"Sección 544","actasContabilizadas":[{"NombreCandidatura":"PAN","Votos":132,"Porcentaje":24.5353,"orden":0},{"NombreCandidatura":"PRI","Votos":51,"Porcentaje":9.4796,"orden":0},{"NombreCandidatura":"PRD","Votos":7,"Porcentaje":1.3011,"orden":0},{"NombreCandidatura":"PT","Votos":70,"Porcentaje":13.0112,"orden":0},{"NombreCandidatura":"VERDE","Votos":99,"Porcentaje":18.4015,"orden":0},{"NombreCandidatura":"MOVIMIENTO CIUDADANO","Votos":63,"Porcentaje":11.7100,"orden":0},{"NombreCandidatura":"PES TLAX","Votos":27,"Porcentaje":5.0186,"orden":0},{"NombreCandidatura":"RSP","Votos":26,"Porcentaje":4.8327,"orden":0},{"NombreCandidatura":"FUERZA SOCIAL POR MÉXICO","Votos":2,"Porcentaje":0.3717,"orden":0},{"NombreCandidatura":"CANDIDATO INDEPENDIENTE","Votos":5,"Porcentaje":0.9294,"orden":0},{"NombreCandidatura":"PAC","Votos":6,"Porcentaje":1.1152,"orden":0},{"NombreCandidatura":"PS","Votos":5,"Porcentaje":0.9294,"orden":0},{"NombreCandidatura":"MORENA","Votos":16,"Porcentaje":2.9740,"orden":0},{"NombreCandidatura":"NUEVA ALIANZA TLAX","Votos":7,"Porcentaje":1.3011,"orden":0},{"NombreCandidatura":"ENCUENTRO SOCIAL","Votos":1,"Porcentaje":0.1859,"orden":0},{"NombreCandidatura":"IMPACTO SOCIAL SÍ","Votos":10,"Porcentaje":1.8587,"orden":0}],"resumenVotacion":{"acumulados":{"total":527,"porcentaje":97.9554},"nulos":{"total":11,"porcentaje":2.0446},"noRegistradas":{"total":0,"porcentaje":0.0},"totalVotos":{"total":538}},"detalleVotosCasillas":[{"detalleCasilla":{"Id":"4ABDA2018DAD6E406263EF0F124317F8F6314F15C605972E99EE537EC09327EA","Casilla":"BÁSICA 01","ClaveURL":"basica1","ViaDigitalizacion":1},"candVotTabla":[{"Partido":"PAN","Votos":132,"Porcentaje":24.5353,"orden":0},{"Partido":"PRI","Votos":51,"Porcentaje":9.4796,"orden":0},{"Partido":"PRD","Votos":7,"Porcentaje":1.3011,"orden":0},{"Partido":"PT","Votos":70,"Porcentaje":13.0112,"orden":0},{"Partido":"VERDE","Votos":99,"Porcentaje":18.4015,"orden":0},{"Partido":"MOVIMIENTO CIUDADANO","Votos":63,"Porcentaje":11.7100,"orden":0},{"Partido":"PES TLAX","Votos":27,"Porcentaje":5.0186,"orden":0},{"Partido":"RSP","Votos":26,"Porcentaje":4.8327,"orden":0},{"Partido":"FUERZA SOCIAL POR MÉXICO","Votos":2,"Porcentaje":0.3717,"orden":0},{"Partido":"CANDIDATO INDEPENDIENTE","Votos":5,"Porcentaje":0.9294,"orden":0},{"Partido":"PAC","Votos":6,"Porcentaje":1.1152,"orden":0},{"Partido":"PS","Votos":5,"Porcentaje":0.9294,"orden":0},{"Partido":"MORENA","Votos":16,"Porcentaje":2.9740,"orden":0},{"Partido":"NUEVA ALIANZA TLAX","Votos":7,"Porcentaje":1.3011,"orden":0},{"Partido":"ENCUENTRO SOCIAL","Votos":1,"Porcentaje":0.1859,"orden":0},{"Partido":"IMPACTO SOCIAL SÍ","Votos":10,"Porcentaje":1.8587,"orden":0}],"resumenVotacion":{"Acumulados":{"total":527,"porcentaje":97.9554},"NoRegistradas":{"total":0,"porcentaje":0.0},"VotosNulos":{"total":11,"porcentaje":2.0446},"Total":538,"Observaciones":null},"estadistica":{"Casilla":"BÁSICA 01","ParticipacionCiudadana":83.6703,"ListaNominal":643}}]},{"SeccionID":545,"Seccion":"Sección 545","actasContabilizadas":[{"NombreCandidatura":"PAN","Votos":54,"Porcentaje":12.6464,"orden":0},{"NombreCandidatura":"PRI","Votos":20,"Porcentaje":4.6838,"orden":0},{"NombreCandidatura":"PRD","Votos":14,"Porcentaje":3.2787,"orden":0},{"NombreCandidatura":"PT","Votos":60,"Porcentaje":14.0515,"orden":0},{"NombreCandidatura":"VERDE","Votos":60,"Porcentaje":14.0515,"orden":0},{"NombreCandidatura":"MOVIMIENTO CIUDADANO","Votos":92,"Porcentaje":21.5457,"orden":0},{"NombreCandidatura":"PES TLAX","Votos":6,"Porcentaje":1.4052,"orden":0},{"NombreCandidatura":"RSP","Votos":27,"Porcentaje":6.3232,"orden":0},{"NombreCandidatura":"FUERZA SOCIAL POR MÉXICO","Votos":9,"Porcentaje":2.1077,"orden":0},{"NombreCandidatura":"CANDIDATO INDEPENDIENTE","Votos":33,"Porcentaje":7.7283,"orden":0},{"NombreCandidatura":"PAC","Votos":5,"Porcentaje":1.1710,"orden":0},{"NombreCandidatura":"PS","Votos":9,"Porcentaje":2.1077,"orden":0},{"NombreCandidatura":"MORENA","Votos":12,"Porcentaje":2.8103,"orden":0},{"NombreCandidatura":"NUEVA ALIANZA TLAX","Votos":6,"Porcentaje":1.4052,"orden":0},{"NombreCandidatura":"ENCUENTRO SOCIAL","Votos":0,"Porcentaje":0.0,"orden":0},{"NombreCandidatura":"IMPACTO SOCIAL SÍ","Votos":9,"Porcentaje":2.1077,"orden":0}],"resumenVotacion":{"acumulados":{"total":416,"porcentaje":97.4239},"nulos":{"total":11,"porcentaje":2.5761},"noRegistradas":{"total":0,"porcentaje":0.0},"totalVotos":{"total":427}},"detalleVotosCasillas":[{"detalleCasilla":{"Id":"9A393C1B7FBE2F723A64360BA5D9F782E72AB2262EF578C9A22719145688D5A7","Casilla":"BÁSICA 01","ClaveURL":"basica1","ViaDigitalizacion":1},"candVotTabla":[{"Partido":"PAN","Votos":54,"Porcentaje":12.6464,"orden":0},{"Partido":"PRI","Votos":20,"Porcentaje":4.6838,"orden":0},{"Partido":"PRD","Votos":14,"Porcentaje":3.2787,"orden":0},{"Partido":"PT","Votos":60,"Porcentaje":14.0515,"orden":0},{"Partido":"VERDE","Votos":60,"Porcentaje":14.0515,"orden":0},{"Partido":"MOVIMIENTO CIUDADANO","Votos":92,"Porcentaje":21.5457,"orden":0},{"Partido":"PES TLAX","Votos":6,"Porcentaje":1.4052,"orden":0},{"Partido":"RSP","Votos":27,"Porcentaje":6.3232,"orden":0},{"Partido":"FUERZA SOCIAL POR MÉXICO","Votos":9,"Porcentaje":2.1077,"orden":0},{"Partido":"CANDIDATO INDEPENDIENTE","Votos":33,"Porcentaje":7.7283,"orden":0},{"Partido":"PAC","Votos":5,"Porcentaje":1.1710,"orden":0},{"Partido":"PS","Votos":9,"Porcentaje":2.1077,"orden":0},{"Partido":"MORENA","Votos":12,"Porcentaje":2.8103,"orden":0},{"Partido":"NUEVA ALIANZA TLAX","Votos":6,"Porcentaje":1.4052,"orden":0},{"Partido":"ENCUENTRO SOCIAL","Votos":0,"Porcentaje":0.0,"orden":0},{"Partido":"IMPACTO SOCIAL SÍ","Votos":9,"Porcentaje":2.1077,"orden":0}],"resumenVotacion":{"Acumulados":{"total":416,"porcentaje":97.4239},"NoRegistradas":{"total":0,"porcentaje":0.0},"VotosNulos":{"total":11,"porcentaje":2.5761},"Total":427,"Observaciones":null},"estadistica":{"Casilla":"BÁSICA 01","ParticipacionCiudadana":69.0939,"ListaNominal":618}}]},{"SeccionID":546,"Seccion":"Sección 546","actasContabilizadas":[{"NombreCandidatura":"PAN","Votos":76,"Porcentaje":12.4183,"orden":0},{"NombreCandidatura":"PRI","Votos":37,"Porcentaje":6.0458,"orden":0},{"NombreCandidatura":"PRD","Votos":21,"Porcentaje":3.4314,"orden":0},{"NombreCandidatura":"PT","Votos":169,"Porcentaje":27.6144,"orden":0},{"NombreCandidatura":"VERDE","Votos":96,"Porcentaje":15.6863,"orden":0},{"NombreCandidatura":"MOVIMIENTO CIUDADANO","Votos":96,"Porcentaje":15.6863,"orden":0},{"NombreCandidatura":"PES TLAX","Votos":5,"Porcentaje":0.8170,"orden":0},{"NombreCandidatura":"RSP","Votos":29,"Porcentaje":4.7386,"orden":0},{"NombreCandidatura":"FUERZA SOCIAL POR MÉXICO","Votos":0,"Porcentaje":0.0,"orden":0},{"NombreCandidatura":"CANDIDATO INDEPENDIENTE","Votos":10,"Porcentaje":1.6340,"orden":0},{"NombreCandidatura":"PAC","Votos":5,"Porcentaje":0.8170,"orden":0},{"NombreCandidatura":"PS","Votos":7,"Porcentaje":1.1438,"orden":0},{"NombreCandidatura":"MORENA","Votos":38,"Porcentaje":6.2092,"orden":0},{"NombreCandidatura":"NUEVA ALIANZA TLAX","Votos":1,"Porcentaje":0.1634,"orden":0},{"NombreCandidatura":"ENCUENTRO SOCIAL","Votos":0,"Porcentaje":0.0,"orden":0},{"NombreCandidatura":"IMPACTO SOCIAL SÍ","Votos":11,"Porcentaje":1.7974,"orden":0}],"resumenVotacion":{"acumulados":{"total":601,"porcentaje":98.2026},"nulos":{"total":11,"porcentaje":1.7974},"noRegistradas":{"total":0,"porcentaje":0.0},"totalVotos":{"total":612}},"detalleVotosCasillas":[{"detalleCasilla":{"Id":"4082CDB4C423A480CCE3AFA25DA09F35B7038AA61BD811DB89EF8004B059FB2E","Casilla":"CONTIGUA 01","ClaveURL":"contigua1","ViaDigitalizacion":1},"candVotTabla":[{"Partido":"PAN","Votos":38,"Porcentaje":12.6246,"orden":0},{"Partido":"PRI","Votos":24,"Porcentaje":7.9734,"orden":0},{"Partido":"PRD","Votos":8,"Porcentaje":2.6578,"orden":0},{"Partido":"PT","Votos":85,"Porcentaje":28.2392,"orden":0},{"Partido":"VERDE","Votos":51,"Porcentaje":16.9435,"orden":0},{"Partido":"MOVIMIENTO CIUDADANO","Votos":37,"Porcentaje":12.2924,"orden":0},{"Partido":"PES TLAX","Votos":3,"Porcentaje":0.9967,"orden":0},{"Partido":"RSP","Votos":15,"Porcentaje":4.9834,"orden":0},{"Partido":"FUERZA SOCIAL POR MÉXICO","Votos":0,"Porcentaje":0.0,"orden":0},{"Partido":"CANDIDATO INDEPENDIENTE","Votos":7,"Porcentaje":2.3256,"orden":0},{"Partido":"PAC","Votos":3,"Porcentaje":0.9967,"orden":0},{"Partido":"PS","Votos":5,"Porcentaje":1.6611,"orden":0},{"Partido":"MORENA","Votos":12,"Porcentaje":3.9867,"orden":0},{"Partido":"NUEVA ALIANZA TLAX","Votos":0,"Porcentaje":0.0,"orden":0},{"Partido":"ENCUENTRO SOCIAL","Votos":0,"Porcentaje":0.0,"orden":0},{"Partido":"IMPACTO SOCIAL SÍ","Votos":8,"Porcentaje":2.6578,"orden":0}],"resumenVotacion":{"Acumulados":{"total":296,"porcentaje":98.3389},"NoRegistradas":{"total":0,"porcentaje":0.0},"VotosNulos":{"total":5,"porcentaje":1.6611},"Total":301,"Observaciones":null},"estadistica":{"Casilla":"CONTIGUA 01","ParticipacionCiudadana":75.8186,"ListaNominal":397}},{"detalleCasilla":{"Id":"6A7DA8F08C7030E2C08488D0C2BDEAEE01B5AEBECA9997147B940722137D209F","Casilla":"BÁSICA 01","ClaveURL":"basica1","ViaDigitalizacion":1},"candVotTabla":[{"Partido":"PAN","Votos":38,"Porcentaje":12.2186,"orden":0},{"Partido":"PRI","Votos":13,"Porcentaje":4.1801,"orden":0},{"Partido":"PRD","Votos":13,"Porcentaje":4.1801,"orden":0},{"Partido":"PT","Votos":84,"Porcentaje":27.0096,"orden":0},{"Partido":"VERDE","Votos":45,"Porcentaje":14.4695,"orden":0},{"Partido":"MOVIMIENTO CIUDADANO","Votos":59,"Porcentaje":18.9711,"orden":0},{"Partido":"PES TLAX","Votos":2,"Porcentaje":0.6431,"orden":0},{"Partido":"RSP","Votos":14,"Porcentaje":4.5016,"orden":0},{"Partido":"FUERZA SOCIAL POR MÉXICO","Votos":0,"Porcentaje":0.0,"orden":0},{"Partido":"CANDIDATO INDEPENDIENTE","Votos":3,"Porcentaje":0.9646,"orden":0},{"Partido":"PAC","Votos":2,"Porcentaje":0.6431,"orden":0},{"Partido":"PS","Votos":2,"Porcentaje":0.6431,"orden":0},{"Partido":"MORENA","Votos":26,"Porcentaje":8.3601,"orden":0},{"Partido":"NUEVA ALIANZA TLAX","Votos":1,"Porcentaje":0.3215,"orden":0},{"Partido":"ENCUENTRO SOCIAL","Votos":0,"Porcentaje":0.0,"orden":0},{"Partido":"IMPACTO SOCIAL SÍ","Votos":3,"Porcentaje":0.9646,"orden":0}],"resumenVotacion":{"Acumulados":{"total":305,"porcentaje":98.0707},"NoRegistradas":{"total":0,"porcentaje":0.0},"VotosNulos":{"total":6,"porcentaje":1.9293},"Total":311,"Observaciones":null},"estadistica":{"Casilla":"BÁSICA 01","ParticipacionCiudadana":78.3375,"ListaNominal":397}}]}]