[{"SeccionId":5,"Seccion":"Sección 5","ListPartidos":null,"groupPartidos":[{"Partido":"PAN","Votos":520,"orden":0},{"Partido":"PRI","Votos":74,"orden":0},{"Partido":"PRD","Votos":9,"orden":0},{"Partido":"PT","Votos":85,"orden":0},{"Partido":"VERDE","Votos":11,"orden":0},{"Partido":"MOVIMIENTO CIUDADANO","Votos":84,"orden":0},{"Partido":"PES TLAX","Votos":152,"orden":0},{"Partido":"RSP","Votos":5,"orden":0},{"Partido":"FUERZA SOCIAL POR MÉXICO","Votos":173,"orden":0},{"Partido":"PAC","Votos":38,"orden":0},{"Partido":"PS","Votos":255,"orden":0},{"Partido":"MORENA","Votos":415,"orden":0},{"Partido":"NUEVA ALIANZA TLAX","Votos":49,"orden":0},{"Partido":"ENCUENTRO SOCIAL","Votos":20,"orden":0},{"Partido":"IMPACTO SOCIAL SÍ","Votos":29,"orden":0}],"resumenVotacion":{"NoRegistradas":0,"VotosNulos":31,"Total":1950,"Observaciones":""}},{"SeccionId":8,"Seccion":"Sección 8","ListPartidos":null,"groupPartidos":[{"Partido":"PAN","Votos":542,"orden":0},{"Partido":"PRI","Votos":68,"orden":0},{"Partido":"PRD","Votos":2,"orden":0},{"Partido":"PT","Votos":53,"orden":0},{"Partido":"VERDE","Votos":6,"orden":0},{"Partido":"MOVIMIENTO CIUDADANO","Votos":38,"orden":0},{"Partido":"PES TLAX","Votos":68,"orden":0},{"Partido":"RSP","Votos":2,"orden":0},{"Partido":"FUERZA SOCIAL POR MÉXICO","Votos":33,"orden":0},{"Partido":"PAC","Votos":36,"orden":0},{"Partido":"PS","Votos":319,"orden":0},{"Partido":"MORENA","Votos":244,"orden":0},{"Partido":"NUEVA ALIANZA TLAX","Votos":40,"orden":0},{"Partido":"ENCUENTRO SOCIAL","Votos":18,"orden":0},{"Partido":"IMPACTO SOCIAL SÍ","Votos":50,"orden":0}],"resumenVotacion":{"NoRegistradas":2,"VotosNulos":24,"Total":1545,"Observaciones":""}},{"SeccionId":9,"Seccion":"Sección 9","ListPartidos":null,"groupPartidos":[{"Partido":"PAN","Votos":343,"orden":0},{"Partido":"PRI","Votos":64,"orden":0},{"Partido":"PRD","Votos":3,"orden":0},{"Partido":"PT","Votos":53,"orden":0},{"Partido":"VERDE","Votos":7,"orden":0},{"Partido":"MOVIMIENTO CIUDADANO","Votos":566,"orden":0},{"Partido":"PES TLAX","Votos":29,"orden":0},{"Partido":"RSP","Votos":8,"orden":0},{"Partido":"FUERZA SOCIAL POR MÉXICO","Votos":67,"orden":0},{"Partido":"PAC","Votos":64,"orden":0},{"Partido":"PS","Votos":128,"orden":0},{"Partido":"MORENA","Votos":309,"orden":0},{"Partido":"NUEVA ALIANZA TLAX","Votos":24,"orden":0},{"Partido":"ENCUENTRO SOCIAL","Votos":9,"orden":0},{"Partido":"IMPACTO SOCIAL SÍ","Votos":63,"orden":0}],"resumenVotacion":{"NoRegistradas":0,"VotosNulos":29,"Total":1766,"Observaciones":""}},{"SeccionId":6,"Seccion":"Sección 6","ListPartidos":null,"groupPartidos":[{"Partido":"PAN","Votos":207,"orden":0},{"Partido":"PRI","Votos":24,"orden":0},{"Partido":"PRD","Votos":6,"orden":0},{"Partido":"PT","Votos":12,"orden":0},{"Partido":"VERDE","Votos":3,"orden":0},{"Partido":"MOVIMIENTO CIUDADANO","Votos":18,"orden":0},{"Partido":"PES TLAX","Votos":23,"orden":0},{"Partido":"RSP","Votos":1,"orden":0},{"Partido":"FUERZA SOCIAL POR MÉXICO","Votos":9,"orden":0},{"Partido":"PAC","Votos":7,"orden":0},{"Partido":"PS","Votos":164,"orden":0},{"Partido":"MORENA","Votos":102,"orden":0},{"Partido":"NUEVA ALIANZA TLAX","Votos":6,"orden":0},{"Partido":"ENCUENTRO SOCIAL","Votos":2,"orden":0},{"Partido":"IMPACTO SOCIAL SÍ","Votos":8,"orden":0}],"resumenVotacion":{"NoRegistradas":0,"VotosNulos":6,"Total":598,"Observaciones":""}},{"SeccionId":10,"Seccion":"Sección 10","ListPartidos":null,"groupPartidos":[{"Partido":"PAN","Votos":317,"orden":0},{"Partido":"PRI","Votos":44,"orden":0},{"Partido":"PRD","Votos":5,"orden":0},{"Partido":"PT","Votos":51,"orden":0},{"Partido":"VERDE","Votos":5,"orden":0},{"Partido":"MOVIMIENTO CIUDADANO","Votos":39,"orden":0},{"Partido":"PES TLAX","Votos":20,"orden":0},{"Partido":"RSP","Votos":9,"orden":0},{"Partido":"FUERZA SOCIAL POR MÉXICO","Votos":89,"orden":0},{"Partido":"PAC","Votos":8,"orden":0},{"Partido":"PS","Votos":393,"orden":0},{"Partido":"MORENA","Votos":234,"orden":0},{"Partido":"NUEVA ALIANZA TLAX","Votos":25,"orden":0},{"Partido":"ENCUENTRO SOCIAL","Votos":1,"orden":0},{"Partido":"IMPACTO SOCIAL SÍ","Votos":226,"orden":0}],"resumenVotacion":{"NoRegistradas":0,"VotosNulos":25,"Total":1491,"Observaciones":""}},{"SeccionId":11,"Seccion":"Sección 11","ListPartidos":null,"groupPartidos":[{"Partido":"PAN","Votos":173,"orden":0},{"Partido":"PRI","Votos":32,"orden":0},{"Partido":"PRD","Votos":0,"orden":0},{"Partido":"PT","Votos":28,"orden":0},{"Partido":"VERDE","Votos":4,"orden":0},{"Partido":"MOVIMIENTO CIUDADANO","Votos":12,"orden":0},{"Partido":"PES TLAX","Votos":13,"orden":0},{"Partido":"RSP","Votos":1,"orden":0},{"Partido":"FUERZA SOCIAL POR MÉXICO","Votos":37,"orden":0},{"Partido":"PAC","Votos":10,"orden":0},{"Partido":"PS","Votos":119,"orden":0},{"Partido":"MORENA","Votos":181,"orden":0},{"Partido":"NUEVA ALIANZA TLAX","Votos":27,"orden":0},{"Partido":"ENCUENTRO SOCIAL","Votos":0,"orden":0},{"Partido":"IMPACTO SOCIAL SÍ","Votos":39,"orden":0}],"resumenVotacion":{"NoRegistradas":0,"VotosNulos":7,"Total":683,"Observaciones":""}},{"SeccionId":7,"Seccion":"Sección 7","ListPartidos":null,"groupPartidos":[{"Partido":"PAN","Votos":75,"orden":0},{"Partido":"PRI","Votos":5,"orden":0},{"Partido":"PRD","Votos":3,"orden":0},{"Partido":"PT","Votos":3,"orden":0},{"Partido":"VERDE","Votos":0,"orden":0},{"Partido":"MOVIMIENTO CIUDADANO","Votos":12,"orden":0},{"Partido":"PES TLAX","Votos":5,"orden":0},{"Partido":"RSP","Votos":2,"orden":0},{"Partido":"FUERZA SOCIAL POR MÉXICO","Votos":2,"orden":0},{"Partido":"PAC","Votos":20,"orden":0},{"Partido":"PS","Votos":48,"orden":0},{"Partido":"MORENA","Votos":40,"orden":0},{"Partido":"NUEVA ALIANZA TLAX","Votos":8,"orden":0},{"Partido":"ENCUENTRO SOCIAL","Votos":0,"orden":0},{"Partido":"IMPACTO SOCIAL SÍ","Votos":2,"orden":0}],"resumenVotacion":{"NoRegistradas":0,"VotosNulos":5,"Total":230,"Observaciones":""}}]